book_notes/__init__.py
book_notes/cli.py
booknotes-0.3.5.dist-info/METADATA
booknotes-0.3.5.dist-info/WHEEL
booknotes-0.3.5.dist-info/entry_points.txt
booknotes-0.3.5.dist-info/top_level.txt
booknotes-0.3.5.dist-info/RECORD
