Metadata-Version: 2.4
Name: booknotes
Version: 0.3.5
Summary: A terminal-based book note-taking app with tags and search
Author: Eren Öğrül
Author-email: termapp@pm.me
License: GPL-3.0-or-later
Classifier: Programming Language :: Python :: 3
Classifier: Environment :: Console :: Curses
Classifier: License :: OSI Approved :: GNU General Public License v3 (GPLv3)
Classifier: Operating System :: OS Independent
Classifier: Topic :: Utilities
Requires-Python: >=3.6
Dynamic: author
Dynamic: author-email
Dynamic: classifier
Dynamic: description
Dynamic: description-content-type
Dynamic: license
Dynamic: requires-python
Dynamic: summary
